{
  "data": [
    {
      "id": "0bdf",
      "name": "gfgfhfhmanjeet SIngh ",
      "email": "webdevlopersunil1997@gmail.com",
      "mobile": "9898985225",
      "city": "Jaipur",
      "state": "rajasthan "
    },
    {
      "id": "abc0",
      "name": "Manjeet SIngh ",
      "email": "PoojaKumari@gmail.com",
      "mobile": "9898985225",
      "city": "Jaipur",
      "state": "rajasthan"
    },
    {
      "id": "6527",
      "name": "Manjeet SIngh ",
      "email": "PoojaKumari@gmail.com",
      "mobile": "9898985225",
      "city": "Jaipur",
      "state": "rajasthan"
    },
    {
      "id": "f6bb",
      "name": "suresh kumar",
      "email": "webdevlopersunil1997@gmail.com",
      "mobile": "9898985225",
      "city": "Jaipur",
      "state": "rajasthan"
    },
    {
      "id": "315c",
      "name": "aaaa",
      "email": "ram@gmail.com",
      "mobile": "959862245",
      "city": "Jaipur",
      "state": "rajasthan city"
    },
    {
      "id": "13d5",
      "name": "nbnbgnxmaaaa",
      "email": "ram@gmail.com",
      "mobile": "959862245",
      "city": "Jaipur",
      "state": "rajasthan"
    },
    {
      "id": "cfa8",
      "name": "aaaa",
      "email": "PoojaKumari@gmail.com",
      "mobile": "9898985225",
      "city": "kotavdggfg",
      "state": "Uttar Pardesh"
    },
    {
      "id": "68c8",
      "name": "aaaa",
      "email": "PoojaKumari@gmail.com",
      "mobile": "9898985225",
      "city": "Jaipur",
      "state": "rajasthan"
    },
    {
      "id": "930c",
      "name": "Pooja Kumari ghxhghg",
      "email": "webdevlopersunil1997@gmail.com",
      "mobile": "9898985225",
      "city": "Jaipur",
      "state": "rajasthan"
    },
    {
      "id": "eecd",
      "name": "yytditjufjyiyuisdsf",
      "email": "PoojaKumari@gmail.com",
      "mobile": "9898985225",
      "city": "udaipurdtyu",
      "state": "yyuyuyuidy"
    },
    {
      "id": "133d",
      "name": "edfETRTRT",
      "email": "ram@gmail.com",
      "mobile": "9898985225",
      "city": "Jaipur",
      "state": "rajasthanTRETET"
    }
  ]
}